README.md
setup.cfg
setup.py
datareport/__init__.py
datareport/reporter.py
datareport/verify.py
datareport.egg-info/PKG-INFO
datareport.egg-info/SOURCES.txt
datareport.egg-info/dependency_links.txt
datareport.egg-info/entry_points.txt
datareport.egg-info/requires.txt
datareport.egg-info/top_level.txt