Metadata-Version: 1.1
Name: datareport
Version: 0.1.7
Summary: Tool to combine YAML datasets with Jinja2-based templates.
Home-page: https://github.com/INM-6/datareport
Author: Dennis Terhorst
Author-email: d.terhorst@fz-juelich.de
License: BSD
Platform: UNKNOWN
Classifier: Development Status :: 2 - Pre-Alpha
Classifier: Intended Audience :: Science/Research
Classifier: License :: OSI Approved :: BSD License
Classifier: Natural Language :: English
Classifier: Operating System :: OS Independent
Classifier: Programming Language :: Python :: 2
Classifier: Programming Language :: Python :: 3
Classifier: Topic :: Scientific/Engineering
